[
    {
        "title": "أي فريق يعتبر الأكثر فوزًا بلقب الدوري السعودي حتى عام 2024؟",
        "Answer-1": "الهلال",
        "Answer-2": " النصر",
        "Answer-3": "الاتحاد",
        "Answer-4": "الأهلي",
        "Correct_Answer": "الهلال"
    },
    
    {
        "title": "من هو الهداف التاريخي للدوري السعودي؟",
        "Answer-1": "ماجد عبد الله",
        "Answer-2": "سامي الجابر",
        "Answer-3": "ناصر الشمراني",
        "Answer-4": " يوسف الثنيان",
        "Correct_Answer": "ماجد عبد الله"
    },

    {
        "title": "ما هو الفريق الذي فاز بأول بطولة دوري سعودي بعد تأسيسه في عام 1976؟",
        "Answer-1": "الهلال",
        "Answer-2": "النصر",
        "Answer-3": "الاتحاد",
        "Answer-4": "الأهلي",
        "Correct_Answer": "الهلال"
    },

    {
        "title": "في أي عام تم تأسيس الدوري السعودي لكرة القدم؟",
        "Answer-1": "1976",
        "Answer-2": "1980",
        "Answer-3": "1984",
        "Answer-4": "1990",
        "Correct_Answer": "1976"
    },

    
    {
        "title": "ما هو الفريق الذي يُلقب بـ الراقي في الدوري السعودي؟",
        "Answer-1": "النصر",
        "Answer-2": "الأهلي",
        "Answer-3": "الاتحاد",
        "Answer-4": "الهلال",
        "Correct_Answer": "الأهلي"
    },

    
    {
        "title": "من هو اللاعب الذي سجل أكثر عدد من الأهداف في موسم واحد من الدوري السعودي؟",
        "Answer-1": "سامي الجابر",
        "Answer-2": "ياسر القحطاني",
        "Answer-3": "عمر السومة",
        "Answer-4": "ماجد عبد الله",
        "Correct_Answer": "عمر السومة"
    },

    
    {
        "title": "من هو اللاعب السعودي الذي حصل على جائزة أفضل لاعب في آسيا عام 1999؟",
        "Answer-1": "ماجد عبد الله",
        "Answer-2": "سامي الجابر",
        "Answer-3": " ياسر القحطاني",
        "Answer-4": "نواف التمياط",
        "Correct_Answer": "سامي الجابر"
    },

    
    {
        "title": "أي من هذه الفرق لم يفز بالدوري السعودي منذ تأسيسه؟",
        "Answer-1": "التعاون",
        "Answer-2": "الشباب",
        "Answer-3": "الفتح",
        "Answer-4": "الرائد",
        "Correct_Answer": "الرائد"
    },

    {
        "title": "من هو اللاعب الذي سجل أسرع هدف في تاريخ الدوري السعودي؟",
        "Answer-1": "ناصر الشمراني",
        "Answer-2": "حسين عبد الغني",
        "Answer-3": "ماجد عبد الله",
        "Answer-4": "سامي الجابر",
        "Correct_Answer": "حسين عبد الغني"
    },

    {
        "title": "من هو اللاعب الذي حصل على جائزة أفضل لاعب في الدوري السعودي موسم 2021-2022؟",
        "Answer-1": "عبد الرزاق حمد الله",
        "Answer-2": "أندريه كاريلو",
        "Answer-3": "سالم الدوسري",
        "Answer-4": "ناصر الشمراني",
        "Correct_Answer": "عبد الرزاق حمد الله"
    }

]

